ml_boilerplate/__init__.py
ml_boilerplate/tools.py
ml_boilerplate/transformers.py
ml_boilerplate-0.2.dist-info/LICENSE
ml_boilerplate-0.2.dist-info/METADATA
ml_boilerplate-0.2.dist-info/WHEEL
ml_boilerplate-0.2.dist-info/top_level.txt
ml_boilerplate-0.2.dist-info/RECORD
