Metadata-Version: 2.1
Name: ml-boilerplate
Version: 0.2
Summary: A collection of useful tools for machine learning.
Home-page: https://github.com/jackbicknell14/ml-boilerplate
Author: Jack Bicknell
Author-email: jakbicknell@gmail.com
License: UNKNOWN
Platform: UNKNOWN
Classifier: Programming Language :: Python :: 3
Classifier: License :: OSI Approved :: MIT License
Classifier: Operating System :: OS Independent
Requires-Dist: scikit-learn
Requires-Dist: pandas
Requires-Dist: xgboost
Requires-Dist: numpy
Requires-Dist: scipy
